django_impostor/__init__.py
django_impostor-0.1.0.dist-info/WHEEL
django_impostor-0.1.0.dist-info/METADATA
django_impostor-0.1.0.dist-info/RECORD
