Metadata-Version: 2.1
Name: django-impostor
Version: 0.1.0
Summary: Pretend to be someone else, if you are a superuser, in Django
License: MIT
Author: Paris Kasidiaris
Author-email: paris@withlogic.co
Requires-Python: >=3.8,<4.0
Classifier: License :: OSI Approved :: MIT License
Classifier: Programming Language :: Python :: 3
Classifier: Programming Language :: Python :: 3.8
Classifier: Programming Language :: Python :: 3.9
